DIRestInvoker-0.2.2.dist-info/METADATA
DIRestInvoker-0.2.2.dist-info/RECORD
DIRestInvoker-0.2.2.dist-info/WHEEL
DIRestInvoker-0.2.2.dist-info/top_level.txt
direstinvoker/__init__.py
direstinvoker/ifind.py
direstinvoker/iwind.py
direstinvoker/utils/__init__.py
direstinvoker/utils/fh_utils.py
