Metadata-Version: 2.1
Name: DIRestInvoker
Version: 0.2.2
Summary: 调用 DIRestPlus 接口，实现Wind、iFinD、Choice接口调用
Home-page: https://github.com/DataIntegrationAlliance/DIRestInvoker
Author: MG
Author-email: mmmaaaggg@163.com
License: UNKNOWN
Platform: UNKNOWN
Classifier: Programming Language :: Python :: 3 :: Only
Classifier: Programming Language :: Python :: 3.5
Classifier: Programming Language :: Python :: 3.6
Classifier: Programming Language :: Python :: 3.7
Classifier: License :: OSI Approved :: MIT License
Classifier: Operating System :: MacOS
Classifier: Operating System :: Microsoft :: Windows
Classifier: Operating System :: Unix
Classifier: Operating System :: POSIX
Classifier: Operating System :: OS Independent
Classifier: Development Status :: 5 - Production/Stable
Classifier: Environment :: No Input/Output (Daemon)
Classifier: Intended Audience :: Developers
Classifier: Natural Language :: Chinese (Simplified)
Classifier: Topic :: Software Development
Requires-Python: >=3.5
Requires-Dist: pandas (>=0.23.0)
Requires-Dist: requests (>=2.19.1)
Requires-Dist: xlrd (>=1.1.0)
